{
  "cookies": [
    {
      "name": "_GRECAPTCHA",
      "value": "09ANOXeZxImurikLhRMbroCEy5LCOODKbK1ziIfMxzPkEUG7Ds6igQyEuv-4fc30RIHAzvaUta_mVjCaqW81IMlcI",
      "domain": "www.google.com",
      "path": "/recaptcha",
      "expires": 1748505316.414626,
      "httpOnly": true,
      "secure": true,
      "sameSite": "None"
    },
    {
      "name": "logged_out_uuid",
      "value": "42fc1581fb5996e662669c4d5e09f25e",
      "domain": ".asana.com",
      "path": "/",
      "expires": 1740729319.616259,
      "httpOnly": false,
      "secure": true,
      "sameSite": "None"
    },
    {
      "name": "xsrf_token",
      "value": "2813a00ae714ac8f9e4852adf7b2027b%3A1732953314292",
      "domain": ".asana.com",
      "path": "/",
      "expires": 1734162914.466667,
      "httpOnly": false,
      "secure": true,
      "sameSite": "None"
    },
    {
      "name": "onetrust_banner_consent_required",
      "value": "false",
      "domain": "app.asana.com",
      "path": "/",
      "expires": 1735977315.026518,
      "httpOnly": false,
      "secure": false,
      "sameSite": "Lax"
    },
    {
      "name": "onetrust_banner_previously_shown",
      "value": "false",
      "domain": "app.asana.com",
      "path": "/",
      "expires": 1735977315.026757,
      "httpOnly": false,
      "secure": false,
      "sameSite": "Lax"
    },
    {
      "name": "_gcl_au",
      "value": "1.1.296068883.1732953315",
      "domain": ".asana.com",
      "path": "/",
      "expires": 1740729315,
      "httpOnly": false,
      "secure": false,
      "sameSite": "Lax"
    },
    {
      "name": "_gid",
      "value": "GA1.2.1024568411.1732953316",
      "domain": ".asana.com",
      "path": "/",
      "expires": 1733039715,
      "httpOnly": false,
      "secure": false,
      "sameSite": "Lax"
    },
    {
      "name": "ajs_anonymous_id",
      "value": "feb4c0cc-3136-4c9f-824d-27d11134af53",
      "domain": ".asana.com",
      "path": "/",
      "expires": 1764489315,
      "httpOnly": false,
      "secure": false,
      "sameSite": "Lax"
    },
    {
      "name": "_ga",
      "value": "GA1.1.356006231.1732953316",
      "domain": ".asana.com",
      "path": "/",
      "expires": 1767513315.680359,
      "httpOnly": false,
      "secure": false,
      "sameSite": "Lax"
    },
    {
      "name": "_ga_J1KDXMCQTH",
      "value": "GS1.1.1732953315.1.0.1732953315.0.0.414912261",
      "domain": ".asana.com",
      "path": "/",
      "expires": 1767513315.728882,
      "httpOnly": false,
      "secure": false,
      "sameSite": "Lax"
    },
    {
      "name": "FPID",
      "value": "FPID2.2.DRQr77LZ%2BeOuF3kCLbkxoOxjRJxdpYCLx4ja0mamcHM%3D.1732953316",
      "domain": ".asana.com",
      "path": "/",
      "expires": 1767513315.790258,
      "httpOnly": true,
      "secure": true,
      "sameSite": "Lax"
    },
    {
      "name": "FPLC",
      "value": "99cMa7d8lLf3YLYBvJs0v1fWWCebh8wD%2F0hE2JiEiv93NM1iT2kVP3HFfnlfxGyrKpPdQJVpBOaYgZtQQqpOtAVTMk8NWuAtGRKiF2gRKZz9aM%2BNkQfeY4jwsdbesQ%3D%3D",
      "domain": ".asana.com",
      "path": "/",
      "expires": 1733025315.79031,
      "httpOnly": false,
      "secure": true,
      "sameSite": "Lax"
    },
    {
      "name": "FPGSID",
      "value": "1.1732953315.1732953315.G-J1KDXMCQTH._dF8NGQBp9V-2zVwx2eE5g",
      "domain": ".asana.com",
      "path": "/",
      "expires": 1732955115.790327,
      "httpOnly": false,
      "secure": true,
      "sameSite": "Strict"
    },
    {
      "name": "_fbp",
      "value": "fb.1.1732953315684.1261178723",
      "domain": ".asana.com",
      "path": "/",
      "expires": 1740729315,
      "httpOnly": false,
      "secure": false,
      "sameSite": "Lax"
    },
    {
      "name": "_gtmeec",
      "value": "e30%3D",
      "domain": ".asana.com",
      "path": "/",
      "expires": 1740729315.82303,
      "httpOnly": true,
      "secure": true,
      "sameSite": "Strict"
    },
    {
      "name": "ar_debug",
      "value": "1",
      "domain": ".www.google-analytics.com",
      "path": "/",
      "expires": 1740729315.941913,
      "httpOnly": true,
      "secure": true,
      "sameSite": "None"
    },
    {
      "name": "saml_redirect_url",
      "value": "https%3A%2F%2Fapp.asana.com%2F%3Frr%3D993417",
      "domain": ".app.asana.com",
      "path": "/",
      "expires": 1732953616.153773,
      "httpOnly": true,
      "secure": true,
      "sameSite": "None"
    },
    {
      "name": "user",
      "value": "1205367004044110",
      "domain": ".app.asana.com",
      "path": "/",
      "expires": 1767513317.204058,
      "httpOnly": false,
      "secure": true,
      "sameSite": "Lax"
    },
    {
      "name": "auth_token",
      "value": "05393a82699ed7203868c5a702fea19a6b6505047d28ead79fc257fc948e3d12",
      "domain": ".app.asana.com",
      "path": "/",
      "expires": 1767513317.204072,
      "httpOnly": true,
      "secure": true,
      "sameSite": "Lax"
    },
    {
      "name": "ticket",
      "value": "17e2e0f915f6ebaa03c90ce4b589650e0f2c2e2fb431d6d7ec432b773c10d92a",
      "domain": ".app.asana.com",
      "path": "/",
      "expires": 1767513317.204085,
      "httpOnly": false,
      "secure": true,
      "sameSite": "Lax"
    },
    {
      "name": "user_asana_dot_com",
      "value": "1205367004044110",
      "domain": ".asana.com",
      "path": "/",
      "expires": 1767513317.204096,
      "httpOnly": false,
      "secure": true,
      "sameSite": "Lax"
    },
    {
      "name": "is_logged_in",
      "value": "true",
      "domain": ".asana.com",
      "path": "/",
      "expires": 1767513317.204106,
      "httpOnly": false,
      "secure": false,
      "sameSite": "Lax"
    },
    {
      "name": "last_login_time",
      "value": "1732953316913",
      "domain": ".app.asana.com",
      "path": "/",
      "expires": 1767513317.204116,
      "httpOnly": false,
      "secure": true,
      "sameSite": "Lax"
    },
    {
      "name": "user_cross_site",
      "value": "1205367004044110",
      "domain": ".app.asana.com",
      "path": "/",
      "expires": 1767513317.204125,
      "httpOnly": false,
      "secure": true,
      "sameSite": "None"
    },
    {
      "name": "auth_token_cross_site",
      "value": "05393a82699ed7203868c5a702fea19a6b6505047d28ead79fc257fc948e3d12",
      "domain": ".app.asana.com",
      "path": "/",
      "expires": 1767513317.204135,
      "httpOnly": true,
      "secure": true,
      "sameSite": "None"
    },
    {
      "name": "ticket_cross_site",
      "value": "17e2e0f915f6ebaa03c90ce4b589650e0f2c2e2fb431d6d7ec432b773c10d92a",
      "domain": ".app.asana.com",
      "path": "/",
      "expires": 1767513317.204146,
      "httpOnly": false,
      "secure": true,
      "sameSite": "None"
    },
    {
      "name": "user_session_MTIwNTM2NzAwNDA0NDExMA",
      "value": "eyJwcmUiOiJiZW4rcG9zZUB3b3Jrd2l0aGxvb3AuY29tIiwiYXV0IjoiMDUzOTNhODI2OTllZDcyMDM4NjhjNWE3MDJmZWExOWE2YjY1MDUwNDdkMjhlYWQ3OWZjMjU3ZmM5NDhlM2QxMiIsInRpYyI6IjE3ZTJlMGY5MTVmNmViYWEwM2M5MGNlNGI1ODk2NTBlMGYyYzJlMmZiNDMxZDZkN2VjNDMyYjc3M2MxMGQ5MmEifQ%3D%3D",
      "domain": ".app.asana.com",
      "path": "/",
      "expires": 1767513317.204157,
      "httpOnly": true,
      "secure": true,
      "sameSite": "Lax"
    },
    {
      "name": "lang_pref",
      "value": "en",
      "domain": ".asana.com",
      "path": "/",
      "expires": 1764489317.204171,
      "httpOnly": false,
      "secure": false,
      "sameSite": "Lax"
    },
    {
      "name": "trusted_device_04a03e1ca81c107a4578fff6d5a9519c5d0696af8b6c31e2e8e31e16bd6a9e69",
      "value": "3bfa7340a10d09a50a03be78000378bd",
      "domain": ".app.asana.com",
      "path": "/",
      "expires": 1767513317.204181,
      "httpOnly": true,
      "secure": true,
      "sameSite": "Lax"
    },
    {
      "name": "OptanonConsent",
      "value": "isGpcEnabled=0&datestamp=Fri+Nov+29+2024+23%3A55%3A17+GMT-0800+(Pacific+Standard+Time)&version=202311.1.0&browserGpcFlag=0&isIABGlobal=false&hosts=&consentId=331467ac-821d-4f9a-9a7b-a85993772b3a&interactionCount=1&landingPath=NotLandingPage&groups=C0001%3A1%2CSSPD_BG%3A1%2CC0002%3A1%2CC0004%3A1%2CC0003%3A1&AwaitingReconsent=false",
      "domain": ".asana.com",
      "path": "/",
      "expires": 1764489317,
      "httpOnly": false,
      "secure": false,
      "sameSite": "Lax"
    },
    {
      "name": "last_domain",
      "value": "998035457938027",
      "domain": ".asana.com",
      "path": "/",
      "expires": 1767513317.706691,
      "httpOnly": false,
      "secure": true,
      "sameSite": "Lax"
    }
  ],
  "origins": [
    {
      "origin": "https://app.asana.com",
      "localStorage": [
        {
          "name": "_grecaptcha",
          "value": "09ANOXeZxlbWRcofTqsAiSkZjtBGQyMm3Uzlig1RKh88q57Ldqu6FyIwg1fmo7FH6AB2viq_oPzHXBqJPWIjQ9MolbFTKPNkaWJJ4bC8hNO1FaZtp3uZ0Qx3qQYRd64Mpq"
        },
        {
          "name": "trigger_engine",
          "value": "{\"ungated_trials_delayed_offer_second_session_trigger_spec\":{\"currentAction\":1,\"currentState\":{}}}"
        },
        {
          "name": "shouldShowTrialCalloutCard",
          "value": "{\"value\":false,\"expiration\":\"2024-12-01T07:55:19.715Z\"}"
        }
      ]
    },
    {
      "origin": "https://asana.com",
      "localStorage": [
        {
          "name": "lastExternalReferrer",
          "value": "other"
        },
        {
          "name": "lastExternalReferrerTime",
          "value": "1732953315867"
        },
        {
          "name": "ajs_anonymous_id",
          "value": "\"feb4c0cc-3136-4c9f-824d-27d11134af53\""
        },
        {
          "name": "ajs_user_id",
          "value": "null"
        },
        {
          "name": "ajs_user_traits",
          "value": "{\"ga_id\":\"356006231.1732953316\"}"
        }
      ]
    },
    {
      "origin": "https://www.google.com",
      "localStorage": [
        {
          "name": "rc::a",
          "value": "MWZxczQ5ajF0cjRhbDA="
        },
        {
          "name": "rc::f",
          "value": "0aAHxbesvkzbvsqpoyfFix_Jo61uapRZye4b4ny2eDNvN4ySjVBtAkolhxdIOTefMt0H6Ze7k"
        }
      ]
    }
  ]
}